[
    [
        "3sn6.pdb"
    ], 
    {
        "shuffle": false, 
        "verbose": true, 
        "backend": "json", 
        "backend_parallel": "json", 
        "make_reference": false, 
        "interval": [
            0, 
            null
        ], 
        "prefix": "", 
        "analyze_only": false, 
        "parallel": false, 
        "fileargs": false, 
        "radii": "protor", 
        "get_nrholes": false, 
        "output_dir": "out", 
        "timeout": 0, 
        "filter_id": [], 
        "debug": true, 
        "nworkers": 0, 
        "check": false, 
        "ex": 0.1
    }
]